jincheng_mcp_demo/__init__.py
jincheng_mcp_demo-0.1.0.dist-info/METADATA
jincheng_mcp_demo-0.1.0.dist-info/WHEEL
jincheng_mcp_demo-0.1.0.dist-info/entry_points.txt
jincheng_mcp_demo-0.1.0.dist-info/RECORD
